lakepipe/__init__.py
lakepipe/cli/__init__.py
lakepipe/cli/main.py
lakepipe/core/__init__.py
lakepipe/core/base.py
lakepipe/core/config.py
lakepipe/core/pipeline.py
lakepipe/integrations/__init__.py
lakepipe/integrations/airflow/__init__.py
lakepipe/py.typed
lakepipe/sources/__init__.py
lakepipe/sources/hive.py
lakepipe/storage/__init__.py
lakepipe/storage/obs.py
lakepipe/targets/__init__.py
lakepipe/targets/teradata.py
lakepipe/utils/__init__.py
lakepipe/utils/logger.py
lakepipe/validation/__init__.py
lakepipe-0.1.0.dist-info/WHEEL
lakepipe-0.1.0.dist-info/entry_points.txt
lakepipe-0.1.0.dist-info/METADATA
lakepipe-0.1.0.dist-info/RECORD
