Metadata-Version: 2.3
Name: lakepipe
Version: 0.1.0
Summary: Modern data transfer for cloud data lakes - High-performance pipelines via object storage
Keywords: data-engineering,etl,data-pipeline,data-lake,sqoop,teradata,hive
Author: Md. Rakibul Hasan
Classifier: Development Status :: 3 - Alpha
Classifier: Intended Audience :: Developers
Classifier: Topic :: Database
Classifier: Topic :: Software Development :: Libraries :: Python Modules
Classifier: License :: OSI Approved :: Apache Software License
Classifier: Programming Language :: Python :: 3
Classifier: Programming Language :: Python :: 3.10
Classifier: Programming Language :: Python :: 3.11
Classifier: Programming Language :: Python :: 3.12
Requires-Dist: pyyaml>=6.0
Requires-Dist: pydantic>=2.0
Requires-Dist: rich>=13.0
Requires-Dist: typer>=0.12.0
Requires-Dist: jinja2>=3.1.0
Requires-Dist: pandas>=2.0
Requires-Dist: pyarrow>=14.0
Requires-Dist: apache-airflow>=2.8.0 ; extra == 'airflow'
Requires-Dist: lakepipe[dev,airflow,sources] ; extra == 'all'
Requires-Dist: pytest>=8.0 ; extra == 'dev'
Requires-Dist: pytest-cov>=4.1 ; extra == 'dev'
Requires-Dist: black>=24.0 ; extra == 'dev'
Requires-Dist: ruff>=0.3.0 ; extra == 'dev'
Requires-Dist: mypy>=1.8 ; extra == 'dev'
Requires-Dist: sqlalchemy>=2.0 ; extra == 'sources'
Requires-Python: >=3.10
Project-URL: Documentation, https://lakepipe.readthedocs.io
Project-URL: Homepage, https://github.com/pesnik/lakepipe
Project-URL: Issues, https://github.com/pesnik/lakepipe/issues
Project-URL: Repository, https://github.com/pesnik/lakepipe
Provides-Extra: airflow
Provides-Extra: all
Provides-Extra: dev
Provides-Extra: sources
